epochai/__init__.py
epochai/airtable/__init__.py
epochai/airtable/client.py
epochai/airtable/models.py
epochai-0.1.3.dist-info/LICENSE
epochai-0.1.3.dist-info/METADATA
epochai-0.1.3.dist-info/WHEEL
epochai-0.1.3.dist-info/RECORD
