Metadata-Version: 2.1
Name: epochai
Version: 0.1.3
Summary: Top-level package for Epoch AI client library.
Home-page: https://github.com/epoch-research/epochai-python
License: MIT
Author: Tom Adamczewski
Author-email: tadamczewskipublic@gmail.com
Requires-Python: >=3.9,<4
Classifier: License :: OSI Approved :: MIT License
Classifier: Natural Language :: English
Classifier: Programming Language :: Python :: 3
Classifier: Programming Language :: Python :: 3.9
Classifier: Programming Language :: Python :: 3.10
Classifier: Programming Language :: Python :: 3.11
Classifier: Programming Language :: Python :: 3.12
Requires-Dist: environs (>14)
Requires-Dist: pyairtable (>3)
Requires-Dist: rich (>13)
